smoketest/__init__.py
smoketest/__init__.pyc
smoketest/urls.py
smoketest/urls.pyc
smoketest/views.py
smoketest/views.pyc
django_smoketest-1.2.1.dist-info/METADATA
django_smoketest-1.2.1.dist-info/WHEEL
django_smoketest-1.2.1.dist-info/top_level.txt
django_smoketest-1.2.1.dist-info/RECORD
