Metadata-Version: 2.1
Name: django-smoketest
Version: 1.2.1
Summary: Django smoketest framework
Home-page: https://github.com/ccnmtl/django-smoketest
Author: Anders Pearson
Author-email: ctl-dev@columbia.edu
License: BSD
Platform: any
Requires-Dist: Django (>=1.8)
